{
  "strategy": "me",
  "param_names": [
    "stop_loss.initial_r",
    "stop_loss.trailing.activation_r",
    "stop_loss.trailing.trail_r"
  ],
  "param_values": [
    [
      1.0,
      1.5,
      2.0,
      2.5,
      3.0
    ],
    [
      0.5,
      1.0,
      1.5,
      2.0,
      2.5,
      3.0
    ],
    [
      0.5,
      1.0,
      1.5,
      2.0,
      2.5
    ]
  ],
  "total_combinations": 150,
  "best": {
    "combo_idx": 141,
    "sharpe": 0.4686756932016538,
    "sharpe_ann": 8.54638958762934,
    "mean_r": 34.784867951132554,
    "std_r": 74.2194836551208,
    "win_rate": 0.5976714100905562,
    "trades": 773,
    "stop_loss.initial_r": 3.0,
    "stop_loss.trailing.activation_r": 2.5,
    "stop_loss.trailing.trail_r": 0.5
  },
  "plateau": {
    "is_plateau": true,
    "mean_sharpe": 0.46631379102183196,
    "std_sharpe": 0.000956590571745062,
    "cv": 0.002051388121395441
  },
  "results": [
    {
      "combo_idx": 1,
      "sharpe": 0.4339306284995586,
      "sharpe_ann": 7.912806785067123,
      "mean_r": 29.994074812157237,
      "std_r": 69.12182003807953,
      "win_rate": 0.6183699870633894,
      "trades": 773,
      "stop_loss.initial_r": 1.0,
      "stop_loss.trailing.activation_r": 0.5,
      "stop_loss.trailing.trail_r": 0.5
    },
    {
      "combo_idx": 2,
      "sharpe": 0.43699135069512013,
      "sharpe_ann": 7.968619631097348,
      "mean_r": 30.504840335744557,
      "std_r": 69.80650826891802,
      "win_rate": 0.5705045278137129,
      "trades": 773,
      "stop_loss.initial_r": 1.0,
      "stop_loss.trailing.activation_r": 0.5,
      "stop_loss.trailing.trail_r": 1.0
    },
    {
      "combo_idx": 3,
      "sharpe": 0.4407170841308952,
      "sharpe_ann": 8.036559082414467,
      "mean_r": 31.096907423962268,
      "std_r": 70.55979571403755,
      "win_rate": 0.5498059508408797,
      "trades": 773,
      "stop_loss.initial_r": 1.0,
      "stop_loss.trailing.activation_r": 0.5,
      "stop_loss.trailing.trail_r": 1.5
    },
    {
      "combo_idx": 4,
      "sharpe": 0.44328247594196374,
      "sharpe_ann": 8.08333948553828,
      "mean_r": 31.399332109044316,
      "std_r": 70.83368689980706,
      "win_rate": 0.536869340232859,
      "trades": 773,
      "stop_loss.initial_r": 1.0,
      "stop_loss.trailing.activation_r": 0.5,
      "stop_loss.trailing.trail_r": 2.0
    },
    {
      "combo_idx": 5,
      "sharpe": 0.4477619942394049,
      "sharpe_ann": 8.165024345858898,
      "mean_r": 31.705431954990033,
      "std_r": 70.80867148817926,
      "win_rate": 0.536869340232859,
      "trades": 773,
      "stop_loss.initial_r": 1.0,
      "stop_loss.trailing.activation_r": 0.5,
      "stop_loss.trailing.trail_r": 2.5
    },
    {
      "combo_idx": 6,
      "sharpe": 0.4425726413786524,
      "sharpe_ann": 8.070395518507727,
      "mean_r": 31.361433586186287,
      "std_r": 70.86166349662439,
      "win_rate": 0.5795601552393272,
      "trades": 773,
      "stop_loss.initial_r": 1.0,
      "stop_loss.trailing.activation_r": 1.0,
      "stop_loss.trailing.trail_r": 0.5
    },
    {
      "combo_idx": 7,
      "sharpe": 0.44290077534448447,
      "sharpe_ann": 8.076379103211634,
      "mean_r": 31.47849618653254,
      "std_r": 71.07347274804121,
      "win_rate": 0.5795601552393272,
      "trades": 773,
      "stop_loss.initial_r": 1.0,
      "stop_loss.trailing.activation_r": 1.0,
      "stop_loss.trailing.trail_r": 1.0
    },
    {
      "combo_idx": 8,
      "sharpe": 0.4426409799961706,
      "sharpe_ann": 8.071641686076607,
      "mean_r": 31.422102988707564,
      "std_r": 70.9877856066996,
      "win_rate": 0.5523932729624839,
      "trades": 773,
      "stop_loss.initial_r": 1.0,
      "stop_loss.trailing.activation_r": 1.0,
      "stop_loss.trailing.trail_r": 1.5
    },
    {
      "combo_idx": 9,
      "sharpe": 0.44328247594196374,
      "sharpe_ann": 8.08333948553828,
      "mean_r": 31.399332109044316,
      "std_r": 70.83368689980706,
      "win_rate": 0.536869340232859,
      "trades": 773,
      "stop_loss.initial_r": 1.0,
      "stop_loss.trailing.activation_r": 1.0,
      "stop_loss.trailing.trail_r": 2.0
    },
    {
      "combo_idx": 10,
      "sharpe": 0.4477619942394049,
      "sharpe_ann": 8.165024345858898,
      "mean_r": 31.705431954990033,
      "std_r": 70.80867148817926,
      "win_rate": 0.536869340232859,
      "trades": 773,
      "stop_loss.initial_r": 1.0,
      "stop_loss.trailing.activation_r": 1.0,
      "stop_loss.trailing.trail_r": 2.5
    },
    {
      "combo_idx": 11,
      "sharpe": 0.44691102794292054,
      "sharpe_ann": 8.149506815077611,
      "mean_r": 31.81655106820281,
      "std_r": 71.19213686592316,
      "win_rate": 0.5588615782664942,
      "trades": 773,
      "stop_loss.initial_r": 1.0,
      "stop_loss.trailing.activation_r": 1.5,
      "stop_loss.trailing.trail_r": 0.5
    },
    {
      "combo_idx": 12,
      "sharpe": 0.4453258223165935,
      "sharpe_ann": 8.120600291748987,
      "mean_r": 31.66379293302338,
      "std_r": 71.10253065566178,
      "win_rate": 0.5588615782664942,
      "trades": 773,
      "stop_loss.initial_r": 1.0,
      "stop_loss.trailing.activation_r": 1.5,
      "stop_loss.trailing.trail_r": 1.0
    },
    {
      "combo_idx": 13,
      "sharpe": 0.44513283426533184,
      "sharpe_ann": 8.117081118265565,
      "mean_r": 31.610616790271237,
      "std_r": 71.01389598105672,
      "win_rate": 0.5588615782664942,
      "trades": 773,
      "stop_loss.initial_r": 1.0,
      "stop_loss.trailing.activation_r": 1.5,
      "stop_loss.trailing.trail_r": 1.5
    },
    {
      "combo_idx": 14,
      "sharpe": 0.44584294546420844,
      "sharpe_ann": 8.130030129797783,
      "mean_r": 31.591013767389704,
      "std_r": 70.85682096976407,
      "win_rate": 0.5407503234152652,
      "trades": 773,
      "stop_loss.initial_r": 1.0,
      "stop_loss.trailing.activation_r": 1.5,
      "stop_loss.trailing.trail_r": 2.0
    },
    {
      "combo_idx": 15,
      "sharpe": 0.4477619942394049,
      "sharpe_ann": 8.165024345858898,
      "mean_r": 31.705431954990033,
      "std_r": 70.80867148817926,
      "win_rate": 0.536869340232859,
      "trades": 773,
      "stop_loss.initial_r": 1.0,
      "stop_loss.trailing.activation_r": 1.5,
      "stop_loss.trailing.trail_r": 2.5
    },
    {
      "combo_idx": 16,
      "sharpe": 0.44868537501212424,
      "sharpe_ann": 8.181862368260862,
      "mean_r": 31.9289102275524,
      "std_r": 71.1610228585891,
      "win_rate": 0.5446313065976714,
      "trades": 773,
      "stop_loss.initial_r": 1.0,
      "stop_loss.trailing.activation_r": 2.0,
      "stop_loss.trailing.trail_r": 0.5
    },
    {
      "combo_idx": 17,
      "sharpe": 0.44713907492459143,
      "sharpe_ann": 8.153665294763913,
      "mean_r": 31.778047911679206,
      "std_r": 71.06971788819502,
      "win_rate": 0.5446313065976714,
      "trades": 773,
      "stop_loss.initial_r": 1.0,
      "stop_loss.trailing.activation_r": 2.0,
      "stop_loss.trailing.trail_r": 1.0
    },
    {
      "combo_idx": 18,
      "sharpe": 0.4465255096399229,
      "sharpe_ann": 8.142476816171392,
      "mean_r": 31.69785664139982,
      "std_r": 70.98778447610059,
      "win_rate": 0.5446313065976714,
      "trades": 773,
      "stop_loss.initial_r": 1.0,
      "stop_loss.trailing.activation_r": 2.0,
      "stop_loss.trailing.trail_r": 1.5
    },
    {
      "combo_idx": 19,
      "sharpe": 0.4462756366044473,
      "sharpe_ann": 8.137920334280834,
      "mean_r": 31.618915497649372,
      "std_r": 70.85064230309874,
      "win_rate": 0.5446313065976714,
      "trades": 773,
      "stop_loss.initial_r": 1.0,
      "stop_loss.trailing.activation_r": 2.0,
      "stop_loss.trailing.trail_r": 2.0
    },
    {
      "combo_idx": 20,
      "sharpe": 0.44769251192525245,
      "sharpe_ann": 8.163757322766362,
      "mean_r": 31.701352255781416,
      "std_r": 70.81054833696734,
      "win_rate": 0.536869340232859,
      "trades": 773,
      "stop_loss.initial_r": 1.0,
      "stop_loss.trailing.activation_r": 2.0,
      "stop_loss.trailing.trail_r": 2.5
    },
    {
      "combo_idx": 21,
      "sharpe": 0.4493176480440953,
      "sharpe_ann": 8.193391986150928,
      "mean_r": 31.969181783345565,
      "std_r": 71.15051439111994,
      "win_rate": 0.538163001293661,
      "trades": 773,
      "stop_loss.initial_r": 1.0,
      "stop_loss.trailing.activation_r": 2.5,
      "stop_loss.trailing.trail_r": 0.5
    },
    {
      "combo_idx": 22,
      "sharpe": 0.44782827691493565,
      "sharpe_ann": 8.166233022938195,
      "mean_r": 31.821553620124376,
      "std_r": 71.05749069563295,
      "win_rate": 0.538163001293661,
      "trades": 773,
      "stop_loss.initial_r": 1.0,
      "stop_loss.trailing.activation_r": 2.5,
      "stop_loss.trailing.trail_r": 1.0
    },
    {
      "combo_idx": 23,
      "sharpe": 0.44680172614339586,
      "sharpe_ann": 8.147513676165318,
      "mean_r": 31.714881279082135,
      "std_r": 70.98200258273758,
      "win_rate": 0.538163001293661,
      "trades": 773,
      "stop_loss.initial_r": 1.0,
      "stop_loss.trailing.activation_r": 2.5,
      "stop_loss.trailing.trail_r": 1.5
    },
    {
      "combo_idx": 24,
      "sharpe": 0.44642033071601567,
      "sharpe_ann": 8.14055885867294,
      "mean_r": 31.627801755326235,
      "std_r": 70.84758372137365,
      "win_rate": 0.538163001293661,
      "trades": 773,
      "stop_loss.initial_r": 1.0,
      "stop_loss.trailing.activation_r": 2.5,
      "stop_loss.trailing.trail_r": 2.0
    },
    {
      "combo_idx": 25,
      "sharpe": 0.44777564469397513,
      "sharpe_ann": 8.16527326447042,
      "mean_r": 31.706453678466076,
      "std_r": 70.80879465906487,
      "win_rate": 0.538163001293661,
      "trades": 773,
      "stop_loss.initial_r": 1.0,
      "stop_loss.trailing.activation_r": 2.5,
      "stop_loss.trailing.trail_r": 2.5
    },
    {
      "combo_idx": 26,
      "sharpe": 0.4493362578468996,
      "sharpe_ann": 8.193731339412087,
      "mean_r": 31.971334863577273,
      "std_r": 71.15235929718969,
      "win_rate": 0.5291073738680466,
      "trades": 773,
      "stop_loss.initial_r": 1.0,
      "stop_loss.trailing.activation_r": 3.0,
      "stop_loss.trailing.trail_r": 0.5
    },
    {
      "combo_idx": 27,
      "sharpe": 0.44792402314462265,
      "sharpe_ann": 8.167978973479947,
      "mean_r": 31.828234514068885,
      "std_r": 71.05721700439452,
      "win_rate": 0.5291073738680466,
      "trades": 773,
      "stop_loss.initial_r": 1.0,
      "stop_loss.trailing.activation_r": 3.0,
      "stop_loss.trailing.trail_r": 1.0
    },
    {
      "combo_idx": 28,
      "sharpe": 0.4469748561683432,
      "sharpe_ann": 8.150670734796645,
      "mean_r": 31.726089986739453,
      "std_r": 70.97958542614424,
      "win_rate": 0.5291073738680466,
      "trades": 773,
      "stop_loss.initial_r": 1.0,
      "stop_loss.trailing.activation_r": 3.0,
      "stop_loss.trailing.trail_r": 1.5
    },
    {
      "combo_idx": 29,
      "sharpe": 0.44695066758229723,
      "sharpe_ann": 8.150229651371749,
      "mean_r": 31.662171874187152,
      "std_r": 70.8404174569382,
      "win_rate": 0.5291073738680466,
      "trades": 773,
      "stop_loss.initial_r": 1.0,
      "stop_loss.trailing.activation_r": 3.0,
      "stop_loss.trailing.trail_r": 2.0
    },
    {
      "combo_idx": 30,
      "sharpe": 0.44838554582965867,
      "sharpe_ann": 8.17639492661569,
      "mean_r": 31.7453516110398,
      "std_r": 70.79923049771956,
      "win_rate": 0.5291073738680466,
      "trades": 773,
      "stop_loss.initial_r": 1.0,
      "stop_loss.trailing.activation_r": 3.0,
      "stop_loss.trailing.trail_r": 2.5
    },
    {
      "combo_idx": 31,
      "sharpe": 0.4414682291603456,
      "sharpe_ann": 8.050256353580037,
      "mean_r": 31.607083211675477,
      "std_r": 71.59537453417848,
      "win_rate": 0.6416558861578266,
      "trades": 773,
      "stop_loss.initial_r": 1.5,
      "stop_loss.trailing.activation_r": 0.5,
      "stop_loss.trailing.trail_r": 0.5
    },
    {
      "combo_idx": 32,
      "sharpe": 0.4444493005791282,
      "sharpe_ann": 8.104616752685482,
      "mean_r": 32.10620578571557,
      "std_r": 72.238173721683,
      "win_rate": 0.5899094437257438,
      "trades": 773,
      "stop_loss.initial_r": 1.5,
      "stop_loss.trailing.activation_r": 0.5,
      "stop_loss.trailing.trail_r": 1.0
    },
    {
      "combo_idx": 33,
      "sharpe": 0.44832623178504755,
      "sharpe_ann": 8.175313323834454,
      "mean_r": 32.70112513744957,
      "std_r": 72.94046794283567,
      "win_rate": 0.5692108667529108,
      "trades": 773,
      "stop_loss.initial_r": 1.5,
      "stop_loss.trailing.activation_r": 0.5,
      "stop_loss.trailing.trail_r": 1.5
    },
    {
      "combo_idx": 34,
      "sharpe": 0.45076646126606157,
      "sharpe_ann": 8.219811368282837,
      "mean_r": 32.992478472265184,
      "std_r": 73.19195483088885,
      "win_rate": 0.5588615782664942,
      "trades": 773,
      "stop_loss.initial_r": 1.5,
      "stop_loss.trailing.activation_r": 0.5,
      "stop_loss.trailing.trail_r": 2.0
    },
    {
      "combo_idx": 35,
      "sharpe": 0.462847140787734,
      "sharpe_ann": 8.440104835968786,
      "mean_r": 33.912493053744456,
      "std_r": 73.26931521285348,
      "win_rate": 0.5679172056921087,
      "trades": 773,
      "stop_loss.initial_r": 1.5,
      "stop_loss.trailing.activation_r": 0.5,
      "stop_loss.trailing.trail_r": 2.5
    },
    {
      "combo_idx": 36,
      "sharpe": 0.455909547068375,
      "sharpe_ann": 8.313596507104329,
      "mean_r": 33.44041399985965,
      "std_r": 73.34879081802696,
      "win_rate": 0.6131953428201811,
      "trades": 773,
      "stop_loss.initial_r": 1.5,
      "stop_loss.trailing.activation_r": 1.0,
      "stop_loss.trailing.trail_r": 0.5
    },
    {
      "combo_idx": 37,
      "sharpe": 0.45607101123185934,
      "sharpe_ann": 8.316540836553443,
      "mean_r": 33.54065900641548,
      "std_r": 73.5426242413902,
      "win_rate": 0.6131953428201811,
      "trades": 773,
      "stop_loss.initial_r": 1.5,
      "stop_loss.trailing.activation_r": 1.0,
      "stop_loss.trailing.trail_r": 1.0
    },
    {
      "combo_idx": 38,
      "sharpe": 0.45573464633547817,
      "sharpe_ann": 8.310407159279851,
      "mean_r": 33.47422466524009,
      "std_r": 73.4511298063541,
      "win_rate": 0.5808538163001293,
      "trades": 773,
      "stop_loss.initial_r": 1.5,
      "stop_loss.trailing.activation_r": 1.0,
      "stop_loss.trailing.trail_r": 1.5
    },
    {
      "combo_idx": 39,
      "sharpe": 0.45616231390981404,
      "sharpe_ann": 8.318205758091969,
      "mean_r": 33.43463619178642,
      "std_r": 73.29548095548428,
      "win_rate": 0.5653298835705045,
      "trades": 773,
      "stop_loss.initial_r": 1.5,
      "stop_loss.trailing.activation_r": 1.0,
      "stop_loss.trailing.trail_r": 2.0
    },
    {
      "combo_idx": 40,
      "sharpe": 0.462847140787734,
      "sharpe_ann": 8.440104835968786,
      "mean_r": 33.912493053744456,
      "std_r": 73.26931521285348,
      "win_rate": 0.5679172056921087,
      "trades": 773,
      "stop_loss.initial_r": 1.5,
      "stop_loss.trailing.activation_r": 1.0,
      "stop_loss.trailing.trail_r": 2.5
    },
    {
      "combo_idx": 41,
      "sharpe": 0.4626332069751191,
      "sharpe_ann": 8.436203712579852,
      "mean_r": 34.08411037783447,
      "std_r": 73.67415452230507,
      "win_rate": 0.5912031047865459,
      "trades": 773,
      "stop_loss.initial_r": 1.5,
      "stop_loss.trailing.activation_r": 1.5,
      "stop_loss.trailing.trail_r": 0.5
    },
    {
      "combo_idx": 42,
      "sharpe": 0.46090927050584274,
      "sharpe_ann": 8.404767406186172,
      "mean_r": 33.91518147939502,
      "std_r": 73.58320530670491,
      "win_rate": 0.5912031047865459,
      "trades": 773,
      "stop_loss.initial_r": 1.5,
      "stop_loss.trailing.activation_r": 1.5,
      "stop_loss.trailing.trail_r": 1.0
    },
    {
      "combo_idx": 43,
      "sharpe": 0.4605489631987758,
      "sharpe_ann": 8.39819713454177,
      "mean_r": 33.845834573382845,
      "std_r": 73.49019817199061,
      "win_rate": 0.5912031047865459,
      "trades": 773,
      "stop_loss.initial_r": 1.5,
      "stop_loss.trailing.activation_r": 1.5,
      "stop_loss.trailing.trail_r": 1.5
    },
    {
      "combo_idx": 44,
      "sharpe": 0.4610665302271756,
      "sharpe_ann": 8.407635066840324,
      "mean_r": 33.810060787241284,
      "std_r": 73.33011305457907,
      "win_rate": 0.5730918499353169,
      "trades": 773,
      "stop_loss.initial_r": 1.5,
      "stop_loss.trailing.activation_r": 1.5,
      "stop_loss.trailing.trail_r": 2.0
    },
    {
      "combo_idx": 45,
      "sharpe": 0.46277728515416955,
      "sharpe_ann": 8.43883100532642,
      "mean_r": 33.90830821158159,
      "std_r": 73.27133223551667,
      "win_rate": 0.5679172056921087,
      "trades": 773,
      "stop_loss.initial_r": 1.5,
      "stop_loss.trailing.activation_r": 1.5,
      "stop_loss.trailing.trail_r": 2.5
    },
    {
      "combo_idx": 46,
      "sharpe": 0.4642513907801397,
      "sharpe_ann": 8.465711599211703,
      "mean_r": 34.18935440134965,
      "std_r": 73.64405380433432,
      "win_rate": 0.5769728331177232,
      "trades": 773,
      "stop_loss.initial_r": 1.5,
      "stop_loss.trailing.activation_r": 2.0,
      "stop_loss.trailing.trail_r": 0.5
    },
    {
      "combo_idx": 47,
      "sharpe": 0.4625651546574631,
      "sharpe_ann": 8.434962765742913,
      "mean_r": 34.02232132221643,
      "std_r": 73.55141428110922,
      "win_rate": 0.5769728331177232,
      "trades": 773,
      "stop_loss.initial_r": 1.5,
      "stop_loss.trailing.activation_r": 2.0,
      "stop_loss.trailing.trail_r": 1.0
    },
    {
      "combo_idx": 48,
      "sharpe": 0.4617930512336987,
      "sharpe_ann": 8.42088331430741,
      "mean_r": 33.92595928867702,
      "std_r": 73.4657206253807,
      "win_rate": 0.5769728331177232,
      "trades": 773,
      "stop_loss.initial_r": 1.5,
      "stop_loss.trailing.activation_r": 2.0,
      "stop_loss.trailing.trail_r": 1.5
    },
    {
      "combo_idx": 49,
      "sharpe": 0.46137143151522836,
      "sharpe_ann": 8.413194999286722,
      "mean_r": 33.83084738166655,
      "std_r": 73.32670614337746,
      "win_rate": 0.5769728331177232,
      "trades": 773,
      "stop_loss.initial_r": 1.5,
      "stop_loss.trailing.activation_r": 2.0,
      "stop_loss.trailing.trail_r": 2.0
    },
    {
      "combo_idx": 50,
      "sharpe": 0.4625906959945695,
      "sharpe_ann": 8.435428516838321,
      "mean_r": 33.89711337653856,
      "std_r": 73.27668643153275,
      "win_rate": 0.5679172056921087,
      "trades": 773,
      "stop_loss.initial_r": 1.5,
      "stop_loss.trailing.activation_r": 2.0,
      "stop_loss.trailing.trail_r": 2.5
    },
    {
      "combo_idx": 51,
      "sharpe": 0.46474294492245993,
      "sharpe_ann": 8.474675181630461,
      "mean_r": 34.22194155434528,
      "std_r": 73.63627985800848,
      "win_rate": 0.5692108667529108,
      "trades": 773,
      "stop_loss.initial_r": 1.5,
      "stop_loss.trailing.activation_r": 2.5,
      "stop_loss.trailing.trail_r": 0.5
    },
    {
      "combo_idx": 52,
      "sharpe": 0.46312282753813566,
      "sharpe_ann": 8.445132035815625,
      "mean_r": 34.058789458394465,
      "std_r": 73.54159076857404,
      "win_rate": 0.5692108667529108,
      "trades": 773,
      "stop_loss.initial_r": 1.5,
      "stop_loss.trailing.activation_r": 2.5,
      "stop_loss.trailing.trail_r": 1.0
    },
    {
      "combo_idx": 53,
      "sharpe": 0.4619571669713635,
      "sharpe_ann": 8.423875995711397,
      "mean_r": 33.936593184622595,
      "std_r": 73.46264028570923,
      "win_rate": 0.5692108667529108,
      "trades": 773,
      "stop_loss.initial_r": 1.5,
      "stop_loss.trailing.activation_r": 2.5,
      "stop_loss.trailing.trail_r": 1.5
    },
    {
      "combo_idx": 54,
      "sharpe": 0.46141740856953234,
      "sharpe_ann": 8.414033399536345,
      "mean_r": 33.83398972813708,
      "std_r": 73.32620984766884,
      "win_rate": 0.5692108667529108,
      "trades": 773,
      "stop_loss.initial_r": 1.5,
      "stop_loss.trailing.activation_r": 2.5,
      "stop_loss.trailing.trail_r": 2.0
    },
    {
      "combo_idx": 55,
      "sharpe": 0.4625870401934933,
      "sharpe_ann": 8.43536185261676,
      "mean_r": 33.897117718547285,
      "std_r": 73.27727491969647,
      "win_rate": 0.5692108667529108,
      "trades": 773,
      "stop_loss.initial_r": 1.5,
      "stop_loss.trailing.activation_r": 2.5,
      "stop_loss.trailing.trail_r": 2.5
    },
    {
      "combo_idx": 56,
      "sharpe": 0.46468608082401497,
      "sharpe_ann": 8.473638254079258,
      "mean_r": 34.21956682086417,
      "std_r": 73.6401803991709,
      "win_rate": 0.5601552393272963,
      "trades": 773,
      "stop_loss.initial_r": 1.5,
      "stop_loss.trailing.activation_r": 3.0,
      "stop_loss.trailing.trail_r": 0.5
    },
    {
      "combo_idx": 57,
      "sharpe": 0.46314134177585414,
      "sharpe_ann": 8.445469646429435,
      "mean_r": 34.060942538626165,
      "std_r": 73.54329977976916,
      "win_rate": 0.5601552393272963,
      "trades": 773,
      "stop_loss.initial_r": 1.5,
      "stop_loss.trailing.activation_r": 3.0,
      "stop_loss.trailing.trail_r": 1.0
    },
    {
      "combo_idx": 58,
      "sharpe": 0.4620512724984714,
      "sharpe_ann": 8.425592027732428,
      "mean_r": 33.94327407856711,
      "std_r": 73.46213742692247,
      "win_rate": 0.5601552393272963,
      "trades": 773,
      "stop_loss.initial_r": 1.5,
      "stop_loss.trailing.activation_r": 3.0,
      "stop_loss.trailing.trail_r": 1.5
    },
    {
      "combo_idx": 59,
      "sharpe": 0.4618608465787864,
      "sharpe_ann": 8.42211957520114,
      "mean_r": 33.863832033285185,
      "std_r": 73.320421690061,
      "win_rate": 0.5601552393272963,
      "trades": 773,
      "stop_loss.initial_r": 1.5,
      "stop_loss.trailing.activation_r": 3.0,
      "stop_loss.trailing.trail_r": 2.0
    },
    {
      "combo_idx": 60,
      "sharpe": 0.4631080913126147,
      "sharpe_ann": 8.444863317966202,
      "mean_r": 33.931487837408206,
      "std_r": 73.26904555097316,
      "win_rate": 0.5601552393272963,
      "trades": 773,
      "stop_loss.initial_r": 1.5,
      "stop_loss.trailing.activation_r": 3.0,
      "stop_loss.trailing.trail_r": 2.5
    },
    {
      "combo_idx": 61,
      "sharpe": 0.445083822764485,
      "sharpe_ann": 8.11618738431139,
      "mean_r": 31.926408399604135,
      "std_r": 71.7312262694794,
      "win_rate": 0.6558861578266494,
      "trades": 773,
      "stop_loss.initial_r": 2.0,
      "stop_loss.trailing.activation_r": 0.5,
      "stop_loss.trailing.trail_r": 0.5
    },
    {
      "combo_idx": 62,
      "sharpe": 0.44831473972506236,
      "sharpe_ann": 8.17510376395494,
      "mean_r": 32.44137735626919,
      "std_r": 72.36295058280817,
      "win_rate": 0.6015523932729625,
      "trades": 773,
      "stop_loss.initial_r": 2.0,
      "stop_loss.trailing.activation_r": 0.5,
      "stop_loss.trailing.trail_r": 1.0
    },
    {
      "combo_idx": 63,
      "sharpe": 0.45207536393943154,
      "sharpe_ann": 8.243679455194902,
      "mean_r": 33.029181572168795,
      "std_r": 73.06122873927278,
      "win_rate": 0.5808538163001293,
      "trades": 773,
      "stop_loss.initial_r": 2.0,
      "stop_loss.trailing.activation_r": 0.5,
      "stop_loss.trailing.trail_r": 1.5
    },
    {
      "combo_idx": 64,
      "sharpe": 0.45441236696532344,
      "sharpe_ann": 8.286295145781073,
      "mean_r": 33.313419771149974,
      "std_r": 73.31098841702992,
      "win_rate": 0.5705045278137129,
      "trades": 773,
      "stop_loss.initial_r": 2.0,
      "stop_loss.trailing.activation_r": 0.5,
      "stop_loss.trailing.trail_r": 2.0
    },
    {
      "combo_idx": 65,
      "sharpe": 0.46629309583900785,
      "sharpe_ann": 8.502942475720191,
      "mean_r": 34.22003732635474,
      "std_r": 73.3873986806134,
      "win_rate": 0.5782664941785253,
      "trades": 773,
      "stop_loss.initial_r": 2.0,
      "stop_loss.trailing.activation_r": 0.5,
      "stop_loss.trailing.trail_r": 2.5
    },
    {
      "combo_idx": 66,
      "sharpe": 0.45949513838532835,
      "sharpe_ann": 8.378980440474903,
      "mean_r": 33.76169590021796,
      "std_r": 73.47563244925067,
      "win_rate": 0.6248382923673997,
      "trades": 773,
      "stop_loss.initial_r": 2.0,
      "stop_loss.trailing.activation_r": 1.0,
      "stop_loss.trailing.trail_r": 0.5
    },
    {
      "combo_idx": 67,
      "sharpe": 0.45958434775070794,
      "sharpe_ann": 8.380607190064135,
      "mean_r": 33.85661798779131,
      "std_r": 73.66790917378269,
      "win_rate": 0.6248382923673997,
      "trades": 773,
      "stop_loss.initial_r": 2.0,
      "stop_loss.trailing.activation_r": 1.0,
      "stop_loss.trailing.trail_r": 1.0
    },
    {
      "combo_idx": 68,
      "sharpe": 0.4591748606249095,
      "sharpe_ann": 8.37314011515721,
      "mean_r": 33.784362171842304,
      "std_r": 73.57624528020504,
      "win_rate": 0.592496765847348,
      "trades": 773,
      "stop_loss.initial_r": 2.0,
      "stop_loss.trailing.activation_r": 1.0,
      "stop_loss.trailing.trail_r": 1.5
    },
    {
      "combo_idx": 69,
      "sharpe": 0.45953070088177156,
      "sharpe_ann": 8.37962892929931,
      "mean_r": 33.73895222361503,
      "std_r": 73.42045299448974,
      "win_rate": 0.5769728331177232,
      "trades": 773,
      "stop_loss.initial_r": 2.0,
      "stop_loss.trailing.activation_r": 1.0,
      "stop_loss.trailing.trail_r": 2.0
    },
    {
      "combo_idx": 70,
      "sharpe": 0.4661415157679124,
      "sharpe_ann": 8.500178384558449,
      "mean_r": 34.21098761079946,
      "std_r": 73.39184872739976,
      "win_rate": 0.5782664941785253,
      "trades": 773,
      "stop_loss.initial_r": 2.0,
      "stop_loss.trailing.activation_r": 1.0,
      "stop_loss.trailing.trail_r": 2.5
    },
    {
      "combo_idx": 71,
      "sharpe": 0.4660296309909778,
      "sharpe_ann": 8.49813814456632,
      "mean_r": 34.39439615917596,
      "std_r": 73.80302425414196,
      "win_rate": 0.6028460543337646,
      "trades": 773,
      "stop_loss.initial_r": 2.0,
      "stop_loss.trailing.activation_r": 1.5,
      "stop_loss.trailing.trail_r": 0.5
    },
    {
      "combo_idx": 72,
      "sharpe": 0.4642399778975433,
      "sharpe_ann": 8.465503483146795,
      "mean_r": 34.220144341754036,
      "std_r": 73.7121875990317,
      "win_rate": 0.6028460543337646,
      "trades": 773,
      "stop_loss.initial_r": 2.0,
      "stop_loss.trailing.activation_r": 1.5,
      "stop_loss.trailing.trail_r": 1.0
    },
    {
      "combo_idx": 73,
      "sharpe": 0.46380626214068915,
      "sharpe_ann": 8.457594594586675,
      "mean_r": 34.144975960968246,
      "std_r": 73.61904904727406,
      "win_rate": 0.6028460543337646,
      "trades": 773,
      "stop_loss.initial_r": 2.0,
      "stop_loss.trailing.activation_r": 1.5,
      "stop_loss.trailing.trail_r": 1.5
    },
    {
      "combo_idx": 74,
      "sharpe": 0.4642515316645547,
      "sharpe_ann": 8.46571416826556,
      "mean_r": 34.10338070005308,
      "std_r": 73.45884369573713,
      "win_rate": 0.5847347994825356,
      "trades": 773,
      "stop_loss.initial_r": 2.0,
      "stop_loss.trailing.activation_r": 1.5,
      "stop_loss.trailing.trail_r": 2.0
    },
    {
      "combo_idx": 75,
      "sharpe": 0.46588754168648405,
      "sharpe_ann": 8.495547119322099,
      "mean_r": 34.195806649619776,
      "std_r": 73.39927254940768,
      "win_rate": 0.5782664941785253,
      "trades": 773,
      "stop_loss.initial_r": 2.0,
      "stop_loss.trailing.activation_r": 1.5,
      "stop_loss.trailing.trail_r": 2.5
    },
    {
      "combo_idx": 76,
      "sharpe": 0.46753022044208836,
      "sharpe_ann": 8.525501675993926,
      "mean_r": 34.49252504685673,
      "std_r": 73.77603316046864,
      "win_rate": 0.5886157826649417,
      "trades": 773,
      "stop_loss.initial_r": 2.0,
      "stop_loss.trailing.activation_r": 2.0,
      "stop_loss.trailing.trail_r": 0.5
    },
    {
      "combo_idx": 77,
      "sharpe": 0.46577823826653925,
      "sharpe_ann": 8.493553950861138,
      "mean_r": 34.32016904874103,
      "std_r": 73.68349619868133,
      "win_rate": 0.5886157826649417,
      "trades": 773,
      "stop_loss.initial_r": 2.0,
      "stop_loss.trailing.activation_r": 2.0,
      "stop_loss.trailing.trail_r": 1.0
    },
    {
      "combo_idx": 78,
      "sharpe": 0.4649323660897576,
      "sharpe_ann": 8.47812931231262,
      "mean_r": 34.21798554042802,
      "std_r": 73.5977704202724,
      "win_rate": 0.5886157826649417,
      "trades": 773,
      "stop_loss.initial_r": 2.0,
      "stop_loss.trailing.activation_r": 2.0,
      "stop_loss.trailing.trail_r": 1.5
    },
    {
      "combo_idx": 79,
      "sharpe": 0.4644376742658617,
      "sharpe_ann": 8.469108513679032,
      "mean_r": 34.11705215864393,
      "std_r": 73.45883861074121,
      "win_rate": 0.5886157826649417,
      "trades": 773,
      "stop_loss.initial_r": 2.0,
      "stop_loss.trailing.activation_r": 2.0,
      "stop_loss.trailing.trail_r": 2.0
    },
    {
      "combo_idx": 80,
      "sharpe": 0.46558178284901913,
      "sharpe_ann": 8.489971549300567,
      "mean_r": 34.17749667874234,
      "std_r": 73.408148552551,
      "win_rate": 0.5782664941785253,
      "trades": 773,
      "stop_loss.initial_r": 2.0,
      "stop_loss.trailing.activation_r": 2.0,
      "stop_loss.trailing.trail_r": 2.5
    },
    {
      "combo_idx": 81,
      "sharpe": 0.4680831210330825,
      "sharpe_ann": 8.535583922465014,
      "mean_r": 34.52903956614708,
      "std_r": 73.76689740475962,
      "win_rate": 0.5808538163001293,
      "trades": 773,
      "stop_loss.initial_r": 2.0,
      "stop_loss.trailing.activation_r": 2.5,
      "stop_loss.trailing.trail_r": 0.5
    },
    {
      "combo_idx": 82,
      "sharpe": 0.46639761968584525,
      "sharpe_ann": 8.504848487764827,
      "mean_r": 34.36056455121379,
      "std_r": 73.67225539092219,
      "win_rate": 0.5808538163001293,
      "trades": 773,
      "stop_loss.initial_r": 2.0,
      "stop_loss.trailing.activation_r": 2.5,
      "stop_loss.trailing.trail_r": 1.0
    },
    {
      "combo_idx": 83,
      "sharpe": 0.4651583532226759,
      "sharpe_ann": 8.482250230268738,
      "mean_r": 34.23254680266832,
      "std_r": 73.5933184161929,
      "win_rate": 0.5808538163001293,
      "trades": 773,
      "stop_loss.initial_r": 2.0,
      "stop_loss.trailing.activation_r": 2.5,
      "stop_loss.trailing.trail_r": 1.5
    },
    {
      "combo_idx": 84,
      "sharpe": 0.46454588266106117,
      "sharpe_ann": 8.471081714157403,
      "mean_r": 34.12412187140919,
      "std_r": 73.45694611678778,
      "win_rate": 0.5808538163001293,
      "trades": 773,
      "stop_loss.initial_r": 2.0,
      "stop_loss.trailing.activation_r": 2.5,
      "stop_loss.trailing.trail_r": 2.0
    },
    {
      "combo_idx": 85,
      "sharpe": 0.46564076375760616,
      "sharpe_ann": 8.491047077283625,
      "mean_r": 34.18142838704579,
      "std_r": 73.40729387867611,
      "win_rate": 0.5808538163001293,
      "trades": 773,
      "stop_loss.initial_r": 2.0,
      "stop_loss.trailing.activation_r": 2.5,
      "stop_loss.trailing.trail_r": 2.5
    },
    {
      "combo_idx": 86,
      "sharpe": 0.46795064440370676,
      "sharpe_ann": 8.53316818616308,
      "mean_r": 34.52213701895318,
      "std_r": 73.7730301941213,
      "win_rate": 0.5717981888745148,
      "trades": 773,
      "stop_loss.initial_r": 2.0,
      "stop_loss.trailing.activation_r": 3.0,
      "stop_loss.trailing.trail_r": 0.5
    },
    {
      "combo_idx": 87,
      "sharpe": 0.46634057734977813,
      "sharpe_ann": 8.503808310016995,
      "mean_r": 34.358189817732686,
      "std_r": 73.67617463826737,
      "win_rate": 0.5717981888745148,
      "trades": 773,
      "stop_loss.initial_r": 2.0,
      "stop_loss.trailing.activation_r": 3.0,
      "stop_loss.trailing.trail_r": 1.0
    },
    {
      "combo_idx": 88,
      "sharpe": 0.46517693952316924,
      "sharpe_ann": 8.482589154960829,
      "mean_r": 34.234699882900024,
      "std_r": 73.59500648934228,
      "win_rate": 0.5717981888745148,
      "trades": 773,
      "stop_loss.initial_r": 2.0,
      "stop_loss.trailing.activation_r": 3.0,
      "stop_loss.trailing.trail_r": 1.5
    },
    {
      "combo_idx": 89,
      "sharpe": 0.4649137898842874,
      "sharpe_ann": 8.477790571705178,
      "mean_r": 34.14943636284449,
      "std_r": 73.45326618800436,
      "win_rate": 0.5717981888745148,
      "trades": 773,
      "stop_loss.initial_r": 2.0,
      "stop_loss.trailing.activation_r": 3.0,
      "stop_loss.trailing.trail_r": 2.0
    },
    {
      "combo_idx": 90,
      "sharpe": 0.466086194938542,
      "sharpe_ann": 8.49916959880965,
      "mean_r": 34.2112706921939,
      "std_r": 73.40116713112472,
      "win_rate": 0.5717981888745148,
      "trades": 773,
      "stop_loss.initial_r": 2.0,
      "stop_loss.trailing.activation_r": 3.0,
      "stop_loss.trailing.trail_r": 2.5
    },
    {
      "combo_idx": 91,
      "sharpe": 0.443432887393022,
      "sharpe_ann": 8.086082266693417,
      "mean_r": 31.83240895693291,
      "std_r": 71.78630602722822,
      "win_rate": 0.6623544631306598,
      "trades": 773,
      "stop_loss.initial_r": 2.5,
      "stop_loss.trailing.activation_r": 0.5,
      "stop_loss.trailing.trail_r": 0.5
    },
    {
      "combo_idx": 92,
      "sharpe": 0.44662669133486543,
      "sharpe_ann": 8.144321883446395,
      "mean_r": 32.34433175038711,
      "std_r": 72.41916432203654,
      "win_rate": 0.6067270375161707,
      "trades": 773,
      "stop_loss.initial_r": 2.5,
      "stop_loss.trailing.activation_r": 0.5,
      "stop_loss.trailing.trail_r": 1.0
    },
    {
      "combo_idx": 93,
      "sharpe": 0.450357225474849,
      "sharpe_ann": 8.21234887650945,
      "mean_r": 32.92944685268779,
      "std_r": 73.11850457815468,
      "win_rate": 0.5847347994825356,
      "trades": 773,
      "stop_loss.initial_r": 2.5,
      "stop_loss.trailing.activation_r": 0.5,
      "stop_loss.trailing.trail_r": 1.5
    },
    {
      "combo_idx": 94,
      "sharpe": 0.45264623981887653,
      "sharpe_ann": 8.254089484438339,
      "mean_r": 33.21045089901697,
      "std_r": 73.36954994325352,
      "win_rate": 0.574385510996119,
      "trades": 773,
      "stop_loss.initial_r": 2.5,
      "stop_loss.trailing.activation_r": 0.5,
      "stop_loss.trailing.trail_r": 2.0
    },
    {
      "combo_idx": 95,
      "sharpe": 0.4644782354692417,
      "sharpe_ann": 8.469848154866439,
      "mean_r": 34.115028188088466,
      "std_r": 73.4480662019041,
      "win_rate": 0.5821474773609314,
      "trades": 773,
      "stop_loss.initial_r": 2.5,
      "stop_loss.trailing.activation_r": 0.5,
      "stop_loss.trailing.trail_r": 2.5
    },
    {
      "combo_idx": 96,
      "sharpe": 0.4576197507483254,
      "sharpe_ann": 8.344782393496702,
      "mean_r": 33.65290555331134,
      "std_r": 73.53901464759821,
      "win_rate": 0.6313065976714101,
      "trades": 773,
      "stop_loss.initial_r": 2.5,
      "stop_loss.trailing.activation_r": 1.0,
      "stop_loss.trailing.trail_r": 0.5
    },
    {
      "combo_idx": 97,
      "sharpe": 0.4576634366327402,
      "sharpe_ann": 8.345579013831625,
      "mean_r": 33.744593488232695,
      "std_r": 73.73233425966606,
      "win_rate": 0.6313065976714101,
      "trades": 773,
      "stop_loss.initial_r": 2.5,
      "stop_loss.trailing.activation_r": 1.0,
      "stop_loss.trailing.trail_r": 1.0
    },
    {
      "combo_idx": 98,
      "sharpe": 0.4572014297206597,
      "sharpe_ann": 8.337154230724474,
      "mean_r": 33.66910351963168,
      "std_r": 73.64172841760968,
      "win_rate": 0.5963777490297542,
      "trades": 773,
      "stop_loss.initial_r": 2.5,
      "stop_loss.trailing.activation_r": 1.0,
      "stop_loss.trailing.trail_r": 1.5
    },
    {
      "combo_idx": 99,
      "sharpe": 0.4575014272214177,
      "sharpe_ann": 8.34262474168543,
      "mean_r": 33.6204594187524,
      "std_r": 73.48711374069889,
      "win_rate": 0.5808538163001293,
      "trades": 773,
      "stop_loss.initial_r": 2.5,
      "stop_loss.trailing.activation_r": 1.0,
      "stop_loss.trailing.trail_r": 2.0
    },
    {
      "combo_idx": 100,
      "sharpe": 0.4640670540822433,
      "sharpe_ann": 8.462350184787248,
      "mean_r": 34.09045453980356,
      "std_r": 73.46019123728173,
      "win_rate": 0.5821474773609314,
      "trades": 773,
      "stop_loss.initial_r": 2.5,
      "stop_loss.trailing.activation_r": 1.0,
      "stop_loss.trailing.trail_r": 2.5
    },
    {
      "combo_idx": 101,
      "sharpe": 0.4646934521217662,
      "sharpe_ann": 8.473772671082877,
      "mean_r": 34.32113416678329,
      "std_r": 73.8575807558182,
      "win_rate": 0.6093143596377749,
      "trades": 773,
      "stop_loss.initial_r": 2.5,
      "stop_loss.trailing.activation_r": 1.5,
      "stop_loss.trailing.trail_r": 0.5
    },
    {
      "combo_idx": 102,
      "sharpe": 0.4628654117875369,
      "sharpe_ann": 8.440438011093368,
      "mean_r": 34.144293436026125,
      "std_r": 73.76721735193931,
      "win_rate": 0.6093143596377749,
      "trades": 773,
      "stop_loss.initial_r": 2.5,
      "stop_loss.trailing.activation_r": 1.5,
      "stop_loss.trailing.trail_r": 1.0
    },
    {
      "combo_idx": 103,
      "sharpe": 0.4623815113785674,
      "sharpe_ann": 8.43161399594461,
      "mean_r": 34.065890902588336,
      "std_r": 73.67485520998143,
      "win_rate": 0.6093143596377749,
      "trades": 773,
      "stop_loss.initial_r": 2.5,
      "stop_loss.trailing.activation_r": 1.5,
      "stop_loss.trailing.trail_r": 1.5
    },
    {
      "combo_idx": 104,
      "sharpe": 0.4627737869379114,
      "sharpe_ann": 8.438767214693712,
      "mean_r": 34.02106148902116,
      "std_r": 73.51553274901812,
      "win_rate": 0.5912031047865459,
      "trades": 773,
      "stop_loss.initial_r": 2.5,
      "stop_loss.trailing.activation_r": 1.5,
      "stop_loss.trailing.trail_r": 2.0
    },
    {
      "combo_idx": 105,
      "sharpe": 0.4643887901401765,
      "sharpe_ann": 8.46821710243493,
      "mean_r": 34.11239363248994,
      "std_r": 73.4565397717569,
      "win_rate": 0.5847347994825356,
      "trades": 773,
      "stop_loss.initial_r": 2.5,
      "stop_loss.trailing.activation_r": 1.5,
      "stop_loss.trailing.trail_r": 2.5
    },
    {
      "combo_idx": 106,
      "sharpe": 0.466072997272237,
      "sharpe_ann": 8.498928936877475,
      "mean_r": 34.41214791862965,
      "std_r": 73.83424510759467,
      "win_rate": 0.5950840879689522,
      "trades": 773,
      "stop_loss.initial_r": 2.5,
      "stop_loss.trailing.activation_r": 2.0,
      "stop_loss.trailing.trail_r": 0.5
    },
    {
      "combo_idx": 107,
      "sharpe": 0.4642825165906376,
      "sharpe_ann": 8.466279184231801,
      "mean_r": 34.23720300717871,
      "std_r": 73.7421759031387,
      "win_rate": 0.5950840879689522,
      "trades": 773,
      "stop_loss.initial_r": 2.5,
      "stop_loss.trailing.activation_r": 2.0,
      "stop_loss.trailing.trail_r": 1.0
    },
    {
      "combo_idx": 108,
      "sharpe": 0.46338701047018865,
      "sharpe_ann": 8.449949461366977,
      "mean_r": 34.13178534621369,
      "std_r": 73.65719058801608,
      "win_rate": 0.5950840879689522,
      "trades": 773,
      "stop_loss.initial_r": 2.5,
      "stop_loss.trailing.activation_r": 2.0,
      "stop_loss.trailing.trail_r": 1.5
    },
    {
      "combo_idx": 109,
      "sharpe": 0.4628407697276286,
      "sharpe_ann": 8.439988658487136,
      "mean_r": 34.0276178117776,
      "std_r": 73.51905890183808,
      "win_rate": 0.5950840879689522,
      "trades": 773,
      "stop_loss.initial_r": 2.5,
      "stop_loss.trailing.activation_r": 2.0,
      "stop_loss.trailing.trail_r": 2.0
    },
    {
      "combo_idx": 110,
      "sharpe": 0.46396451983751413,
      "sharpe_ann": 8.460480453511996,
      "mean_r": 34.08696852577809,
      "std_r": 73.46891210068337,
      "win_rate": 0.5847347994825356,
      "trades": 773,
      "stop_loss.initial_r": 2.5,
      "stop_loss.trailing.activation_r": 2.0,
      "stop_loss.trailing.trail_r": 2.5
    },
    {
      "combo_idx": 111,
      "sharpe": 0.46656020706279305,
      "sharpe_ann": 8.507813299223118,
      "mean_r": 34.444781454737594,
      "std_r": 73.82708797988373,
      "win_rate": 0.5873221216041398,
      "trades": 773,
      "stop_loss.initial_r": 2.5,
      "stop_loss.trailing.activation_r": 2.5,
      "stop_loss.trailing.trail_r": 0.5
    },
    {
      "combo_idx": 112,
      "sharpe": 0.4648360600016422,
      "sharpe_ann": 8.47637315264692,
      "mean_r": 34.27371752646906,
      "std_r": 73.73291462445486,
      "win_rate": 0.5873221216041398,
      "trades": 773,
      "stop_loss.initial_r": 2.5,
      "stop_loss.trailing.activation_r": 2.5,
      "stop_loss.trailing.trail_r": 1.0
    },
    {
      "combo_idx": 113,
      "sharpe": 0.46354781380180077,
      "sharpe_ann": 8.452881740422367,
      "mean_r": 34.14246562527159,
      "std_r": 73.65467942832299,
      "win_rate": 0.5873221216041398,
      "trades": 773,
      "stop_loss.initial_r": 2.5,
      "stop_loss.trailing.activation_r": 2.5,
      "stop_loss.trailing.trail_r": 1.5
    },
    {
      "combo_idx": 114,
      "sharpe": 0.4628839190723167,
      "sharpe_ann": 8.440775494919032,
      "mean_r": 34.03080654136045,
      "std_r": 73.51909439749578,
      "win_rate": 0.5873221216041398,
      "trades": 773,
      "stop_loss.initial_r": 2.5,
      "stop_loss.trailing.activation_r": 2.5,
      "stop_loss.trailing.trail_r": 2.0
    },
    {
      "combo_idx": 115,
      "sharpe": 0.46395843444684454,
      "sharpe_ann": 8.460369485266343,
      "mean_r": 34.08701925089914,
      "std_r": 73.4699850678207,
      "win_rate": 0.5873221216041398,
      "trades": 773,
      "stop_loss.initial_r": 2.5,
      "stop_loss.trailing.activation_r": 2.5,
      "stop_loss.trailing.trail_r": 2.5
    },
    {
      "combo_idx": 116,
      "sharpe": 0.4663524932191349,
      "sharpe_ann": 8.504025598140265,
      "mean_r": 34.43335109383088,
      "std_r": 73.83546050358726,
      "win_rate": 0.5782664941785253,
      "trades": 773,
      "stop_loss.initial_r": 2.5,
      "stop_loss.trailing.activation_r": 3.0,
      "stop_loss.trailing.trail_r": 0.5
    },
    {
      "combo_idx": 117,
      "sharpe": 0.46470363003652876,
      "sharpe_ann": 8.473958267276602,
      "mean_r": 34.26681497927515,
      "std_r": 73.73907317354409,
      "win_rate": 0.5782664941785253,
      "trades": 773,
      "stop_loss.initial_r": 2.5,
      "stop_loss.trailing.activation_r": 3.0,
      "stop_loss.trailing.trail_r": 1.0
    },
    {
      "combo_idx": 118,
      "sharpe": 0.4634908463411236,
      "sharpe_ann": 8.45184292804138,
      "mean_r": 34.14009089179049,
      "std_r": 73.65860871104195,
      "win_rate": 0.5782664941785253,
      "trades": 773,
      "stop_loss.initial_r": 2.5,
      "stop_loss.trailing.activation_r": 3.0,
      "stop_loss.trailing.trail_r": 1.5
    },
    {
      "combo_idx": 119,
      "sharpe": 0.46317551438094046,
      "sharpe_ann": 8.446092790323023,
      "mean_r": 34.051593219082946,
      "std_r": 73.5176885690833,
      "win_rate": 0.5782664941785253,
      "trades": 773,
      "stop_loss.initial_r": 2.5,
      "stop_loss.trailing.activation_r": 3.0,
      "stop_loss.trailing.trail_r": 2.0
    },
    {
      "combo_idx": 120,
      "sharpe": 0.46432725222242166,
      "sharpe_ann": 8.46709494690783,
      "mean_r": 34.11233374233444,
      "std_r": 73.46614608352554,
      "win_rate": 0.5782664941785253,
      "trades": 773,
      "stop_loss.initial_r": 2.5,
      "stop_loss.trailing.activation_r": 3.0,
      "stop_loss.trailing.trail_r": 2.5
    },
    {
      "combo_idx": 121,
      "sharpe": 0.44528606314517666,
      "sharpe_ann": 8.11987527576557,
      "mean_r": 32.150869573796165,
      "std_r": 72.20273041268308,
      "win_rate": 0.6701164294954722,
      "trades": 773,
      "stop_loss.initial_r": 3.0,
      "stop_loss.trailing.activation_r": 0.5,
      "stop_loss.trailing.trail_r": 0.5
    },
    {
      "combo_idx": 122,
      "sharpe": 0.44843712447507195,
      "sharpe_ann": 8.177335472934814,
      "mean_r": 32.65891138406796,
      "std_r": 72.82829543226953,
      "win_rate": 0.6144890038809832,
      "trades": 773,
      "stop_loss.initial_r": 3.0,
      "stop_loss.trailing.activation_r": 0.5,
      "stop_loss.trailing.trail_r": 1.0
    },
    {
      "combo_idx": 123,
      "sharpe": 0.4521246224414522,
      "sharpe_ann": 8.24457769326203,
      "mean_r": 33.240145503186234,
      "std_r": 73.51987450648225,
      "win_rate": 0.592496765847348,
      "trades": 773,
      "stop_loss.initial_r": 3.0,
      "stop_loss.trailing.activation_r": 0.5,
      "stop_loss.trailing.trail_r": 1.5
    },
    {
      "combo_idx": 124,
      "sharpe": 0.4543663858188702,
      "sharpe_ann": 8.285456670910335,
      "mean_r": 33.517268566333016,
      "std_r": 73.76705146426573,
      "win_rate": 0.5821474773609314,
      "trades": 773,
      "stop_loss.initial_r": 3.0,
      "stop_loss.trailing.activation_r": 0.5,
      "stop_loss.trailing.trail_r": 2.0
    },
    {
      "combo_idx": 125,
      "sharpe": 0.4661145714846043,
      "sharpe_ann": 8.499687050474666,
      "mean_r": 34.4179648722221,
      "std_r": 73.84013926575759,
      "win_rate": 0.5899094437257438,
      "trades": 773,
      "stop_loss.initial_r": 3.0,
      "stop_loss.trailing.activation_r": 0.5,
      "stop_loss.trailing.trail_r": 2.5
    },
    {
      "combo_idx": 126,
      "sharpe": 0.460124317990649,
      "sharpe_ann": 8.39045364914704,
      "mean_r": 34.01498428773994,
      "std_r": 73.92563913222952,
      "win_rate": 0.6416558861578266,
      "trades": 773,
      "stop_loss.initial_r": 3.0,
      "stop_loss.trailing.activation_r": 1.0,
      "stop_loss.trailing.trail_r": 0.5
    },
    {
      "combo_idx": 127,
      "sharpe": 0.4601071743999726,
      "sharpe_ann": 8.39014103254034,
      "mean_r": 34.10149757841808,
      "std_r": 74.11642216379252,
      "win_rate": 0.6416558861578266,
      "trades": 773,
      "stop_loss.initial_r": 3.0,
      "stop_loss.trailing.activation_r": 1.0,
      "stop_loss.trailing.trail_r": 1.0
    },
    {
      "combo_idx": 128,
      "sharpe": 0.45959298454477776,
      "sharpe_ann": 8.380764683631606,
      "mean_r": 34.02155187520983,
      "std_r": 74.02539424945277,
      "win_rate": 0.6067270375161707,
      "trades": 773,
      "stop_loss.initial_r": 3.0,
      "stop_loss.trailing.activation_r": 1.0,
      "stop_loss.trailing.trail_r": 1.5
    },
    {
      "combo_idx": 129,
      "sharpe": 0.4598263296176948,
      "sharpe_ann": 8.385019775010207,
      "mean_r": 33.967733130087325,
      "std_r": 73.87078760437339,
      "win_rate": 0.5912031047865459,
      "trades": 773,
      "stop_loss.initial_r": 3.0,
      "stop_loss.trailing.activation_r": 1.0,
      "stop_loss.trailing.trail_r": 2.0
    },
    {
      "combo_idx": 130,
      "sharpe": 0.46630777058332934,
      "sharpe_ann": 8.503210072448354,
      "mean_r": 34.43255360689528,
      "std_r": 73.84083169753264,
      "win_rate": 0.592496765847348,
      "trades": 773,
      "stop_loss.initial_r": 3.0,
      "stop_loss.trailing.activation_r": 1.0,
      "stop_loss.trailing.trail_r": 2.5
    },
    {
      "combo_idx": 131,
      "sharpe": 0.46699837600383737,
      "sharpe_ann": 8.51580339243615,
      "mean_r": 34.67221678219507,
      "std_r": 74.24483373773053,
      "win_rate": 0.6196636481241915,
      "trades": 773,
      "stop_loss.initial_r": 3.0,
      "stop_loss.trailing.activation_r": 1.5,
      "stop_loss.trailing.trail_r": 0.5
    },
    {
      "combo_idx": 132,
      "sharpe": 0.46511128904580645,
      "sharpe_ann": 8.481392006134262,
      "mean_r": 34.49020140719469,
      "std_r": 74.15472859829451,
      "win_rate": 0.6196636481241915,
      "trades": 773,
      "stop_loss.initial_r": 3.0,
      "stop_loss.trailing.activation_r": 1.5,
      "stop_loss.trailing.trail_r": 1.0
    },
    {
      "combo_idx": 133,
      "sharpe": 0.46457496090322026,
      "sharpe_ann": 8.47161196138298,
      "mean_r": 34.407343139149646,
      "std_r": 74.06198360810355,
      "win_rate": 0.6196636481241915,
      "trades": 773,
      "stop_loss.initial_r": 3.0,
      "stop_loss.trailing.activation_r": 1.5,
      "stop_loss.trailing.trail_r": 1.5
    },
    {
      "combo_idx": 134,
      "sharpe": 0.46489962415006464,
      "sharpe_ann": 8.477532256872088,
      "mean_r": 34.35733908133927,
      "std_r": 73.90270350110906,
      "win_rate": 0.6015523932729625,
      "trades": 773,
      "stop_loss.initial_r": 3.0,
      "stop_loss.trailing.activation_r": 1.5,
      "stop_loss.trailing.trail_r": 2.0
    },
    {
      "combo_idx": 135,
      "sharpe": 0.46644451881108756,
      "sharpe_ann": 8.505703702151777,
      "mean_r": 34.44349658056484,
      "std_r": 73.84264406913233,
      "win_rate": 0.5950840879689522,
      "trades": 773,
      "stop_loss.initial_r": 3.0,
      "stop_loss.trailing.activation_r": 1.5,
      "stop_loss.trailing.trail_r": 2.5
    },
    {
      "combo_idx": 136,
      "sharpe": 0.46825482143919495,
      "sharpe_ann": 8.538714911727475,
      "mean_r": 34.756115398207015,
      "std_r": 74.2247891679643,
      "win_rate": 0.6054333764553687,
      "trades": 773,
      "stop_loss.initial_r": 3.0,
      "stop_loss.trailing.activation_r": 2.0,
      "stop_loss.trailing.trail_r": 0.5
    },
    {
      "combo_idx": 137,
      "sharpe": 0.46640509809544506,
      "sharpe_ann": 8.504984857973188,
      "mean_r": 34.57599584251287,
      "std_r": 74.13297149560154,
      "win_rate": 0.6054333764553687,
      "trades": 773,
      "stop_loss.initial_r": 3.0,
      "stop_loss.trailing.activation_r": 2.0,
      "stop_loss.trailing.trail_r": 1.0
    },
    {
      "combo_idx": 138,
      "sharpe": 0.46545845376389466,
      "sharpe_ann": 8.487722620191914,
      "mean_r": 34.4661224469406,
      "std_r": 74.0476881840536,
      "win_rate": 0.6054333764553687,
      "trades": 773,
      "stop_loss.initial_r": 3.0,
      "stop_loss.trailing.activation_r": 2.0,
      "stop_loss.trailing.trail_r": 1.5
    },
    {
      "combo_idx": 139,
      "sharpe": 0.46484768639604634,
      "sharpe_ann": 8.476585162139877,
      "mean_r": 34.3567802682613,
      "std_r": 73.90975855904253,
      "win_rate": 0.6054333764553687,
      "trades": 773,
      "stop_loss.initial_r": 3.0,
      "stop_loss.trailing.activation_r": 2.0,
      "stop_loss.trailing.trail_r": 2.0
    },
    {
      "combo_idx": 140,
      "sharpe": 0.4659028558734739,
      "sharpe_ann": 8.495826376407823,
      "mean_r": 34.410956338018586,
      "std_r": 73.85865079857685,
      "win_rate": 0.5950840879689522,
      "trades": 773,
      "stop_loss.initial_r": 3.0,
      "stop_loss.trailing.activation_r": 2.0,
      "stop_loss.trailing.trail_r": 2.5
    },
    {
      "combo_idx": 141,
      "sharpe": 0.4686756932016538,
      "sharpe_ann": 8.54638958762934,
      "mean_r": 34.784867951132554,
      "std_r": 74.2194836551208,
      "win_rate": 0.5976714100905562,
      "trades": 773,
      "stop_loss.initial_r": 3.0,
      "stop_loss.trailing.activation_r": 2.5,
      "stop_loss.trailing.trail_r": 0.5
    },
    {
      "combo_idx": 142,
      "sharpe": 0.4668920380304637,
      "sharpe_ann": 8.513864299452253,
      "mean_r": 34.60862937862082,
      "std_r": 74.12555057613272,
      "win_rate": 0.5976714100905562,
      "trades": 773,
      "stop_loss.initial_r": 3.0,
      "stop_loss.trailing.activation_r": 2.5,
      "stop_loss.trailing.trail_r": 1.0
    },
    {
      "combo_idx": 143,
      "sharpe": 0.4655540028205932,
      "sharpe_ann": 8.489464975247065,
      "mean_r": 34.47292174281609,
      "std_r": 74.04709557636569,
      "win_rate": 0.5976714100905562,
      "trades": 773,
      "stop_loss.initial_r": 3.0,
      "stop_loss.trailing.activation_r": 2.5,
      "stop_loss.trailing.trail_r": 1.5
    },
    {
      "combo_idx": 144,
      "sharpe": 0.46482591733750306,
      "sharpe_ann": 8.476188199254953,
      "mean_r": 34.356088014661744,
      "std_r": 73.91173067855489,
      "win_rate": 0.5976714100905562,
      "trades": 773,
      "stop_loss.initial_r": 3.0,
      "stop_loss.trailing.activation_r": 2.5,
      "stop_loss.trailing.trail_r": 2.0
    },
    {
      "combo_idx": 145,
      "sharpe": 0.4658319358308551,
      "sharpe_ann": 8.494533136065762,
      "mean_r": 34.40712607995723,
      "std_r": 73.86167291984583,
      "win_rate": 0.5976714100905562,
      "trades": 773,
      "stop_loss.initial_r": 3.0,
      "stop_loss.trailing.activation_r": 2.5,
      "stop_loss.trailing.trail_r": 2.5
    },
    {
      "combo_idx": 146,
      "sharpe": 0.46839332737840494,
      "sharpe_ann": 8.54124059363046,
      "mean_r": 34.768909776513034,
      "std_r": 74.23015603384968,
      "win_rate": 0.5886157826649417,
      "trades": 773,
      "stop_loss.initial_r": 3.0,
      "stop_loss.trailing.activation_r": 3.0,
      "stop_loss.trailing.trail_r": 0.5
    },
    {
      "combo_idx": 147,
      "sharpe": 0.46668468998126406,
      "sharpe_ann": 8.510083268700285,
      "mean_r": 34.597199017714104,
      "std_r": 74.13399188026304,
      "win_rate": 0.5886157826649417,
      "trades": 773,
      "stop_loss.initial_r": 3.0,
      "stop_loss.trailing.activation_r": 3.0,
      "stop_loss.trailing.trail_r": 1.0
    },
    {
      "combo_idx": 148,
      "sharpe": 0.46542182907538365,
      "sharpe_ann": 8.48705476209498,
      "mean_r": 34.46601919562218,
      "std_r": 74.05329325462252,
      "win_rate": 0.5886157826649417,
      "trades": 773,
      "stop_loss.initial_r": 3.0,
      "stop_loss.trailing.activation_r": 3.0,
      "stop_loss.trailing.trail_r": 1.5
    },
    {
      "combo_idx": 149,
      "sharpe": 0.46504094092461745,
      "sharpe_ann": 8.480109194887254,
      "mean_r": 34.372346878671436,
      "std_r": 73.9125179179507,
      "win_rate": 0.5886157826649417,
      "trades": 773,
      "stop_loss.initial_r": 3.0,
      "stop_loss.trailing.activation_r": 3.0,
      "stop_loss.trailing.trail_r": 2.0
    },
    {
      "combo_idx": 150,
      "sharpe": 0.46612375206351503,
      "sharpe_ann": 8.499854460061187,
      "mean_r": 34.42791275767973,
      "std_r": 73.8600266673141,
      "win_rate": 0.5886157826649417,
      "trades": 773,
      "stop_loss.initial_r": 3.0,
      "stop_loss.trailing.activation_r": 3.0,
      "stop_loss.trailing.trail_r": 2.5
    }
  ]
}