{
  "annotations": {
    "list": []
  },
  "editable": true,
  "graphTooltip": 1,
  "id": null,
  "links": [
    {
      "title": "Home",
      "url": "/d/quant-home",
      "type": "link",
      "targetBlank": false
    },
    {
      "title": "Strategy Map",
      "url": "/d/quant-strategy-map",
      "type": "link",
      "targetBlank": false
    },
    {
      "title": "Spot Map",
      "url": "/d/quant-strategy-map-spot",
      "type": "link",
      "targetBlank": false
    },
    {
      "title": "Ops Hub",
      "url": "/d/quant-home",
      "type": "link",
      "targetBlank": false
    },
    {
      "title": "Logs",
      "url": "/d/quant-logs",
      "type": "link",
      "targetBlank": false
    },
    {
      "title": "CMS",
      "url": "http://127.0.0.1:8800",
      "type": "link",
      "targetBlank": true
    }
  ],
  "panels": [
    {
      "type": "row",
      "title": "一眼总览 · 进程 / 管线 / 对账",
      "id": 1100,
      "gridPos": {
        "h": 1,
        "w": 24,
        "x": 0,
        "y": 0
      },
      "collapsed": false
    },
    {
      "type": "stat",
      "title": "FB UP",
      "id": 1101,
      "gridPos": {
        "h": 4,
        "w": 2,
        "x": 0,
        "y": 1
      },
      "datasource": {
        "type": "prometheus",
        "uid": "prometheus-monitoring"
      },
      "targets": [
        {
          "refId": "A",
          "expr": "up{job=\"quant-feature-bus\"}",
          "instant": true,
          "legendFormat": "FB UP"
        }
      ],
      "fieldConfig": {
        "defaults": {
          "min": 0,
          "max": 1.0,
          "decimals": 0,
          "thresholds": {
            "mode": "absolute",
            "steps": [
              {
                "color": "red",
                "value": null
              },
              {
                "color": "green",
                "value": 1
              }
            ]
          }
        },
        "overrides": []
      },
      "options": {
        "reduceOptions": {
          "calcs": [
            "lastNotNull"
          ],
          "values": false
        },
        "colorMode": "background",
        "graphMode": "none"
      }
    },
    {
      "type": "stat",
      "title": "Tr UP",
      "id": 1102,
      "gridPos": {
        "h": 4,
        "w": 2,
        "x": 2,
        "y": 1
      },
      "datasource": {
        "type": "prometheus",
        "uid": "prometheus-monitoring"
      },
      "targets": [
        {
          "refId": "A",
          "expr": "up{job=\"quant-trend-fattail\"}",
          "instant": true,
          "legendFormat": "Tr UP"
        }
      ],
      "fieldConfig": {
        "defaults": {
          "min": 0,
          "max": 1.0,
          "decimals": 0,
          "thresholds": {
            "mode": "absolute",
            "steps": [
              {
                "color": "red",
                "value": null
              },
              {
                "color": "green",
                "value": 1
              }
            ]
          }
        },
        "overrides": []
      },
      "options": {
        "reduceOptions": {
          "calcs": [
            "lastNotNull"
          ],
          "values": false
        },
        "colorMode": "background",
        "graphMode": "none"
      }
    },
    {
      "type": "stat",
      "title": "Hg UP",
      "id": 1103,
      "gridPos": {
        "h": 4,
        "w": 2,
        "x": 4,
        "y": 1
      },
      "datasource": {
        "type": "prometheus",
        "uid": "prometheus-monitoring"
      },
      "targets": [
        {
          "refId": "A",
          "expr": "up{job=\"quant-hedge-multileg\"}",
          "instant": true,
          "legendFormat": "Hg UP"
        }
      ],
      "fieldConfig": {
        "defaults": {
          "min": 0,
          "max": 1.0,
          "decimals": 0,
          "thresholds": {
            "mode": "absolute",
            "steps": [
              {
                "color": "red",
                "value": null
              },
              {
                "color": "green",
                "value": 1
              }
            ]
          }
        },
        "overrides": []
      },
      "options": {
        "reduceOptions": {
          "calcs": [
            "lastNotNull"
          ],
          "values": false
        },
        "colorMode": "background",
        "graphMode": "none"
      }
    },
    {
      "type": "stat",
      "title": "Sp UP",
      "id": 1104,
      "gridPos": {
        "h": 4,
        "w": 2,
        "x": 6,
        "y": 1
      },
      "datasource": {
        "type": "prometheus",
        "uid": "prometheus-monitoring"
      },
      "targets": [
        {
          "refId": "A",
          "expr": "up{job=\"quant-spot-accum\"}",
          "instant": true,
          "legendFormat": "Sp UP"
        }
      ],
      "fieldConfig": {
        "defaults": {
          "min": 0,
          "max": 1.0,
          "decimals": 0,
          "thresholds": {
            "mode": "absolute",
            "steps": [
              {
                "color": "red",
                "value": null
              },
              {
                "color": "green",
                "value": 1
              }
            ]
          }
        },
        "overrides": []
      },
      "options": {
        "reduceOptions": {
          "calcs": [
            "lastNotNull"
          ],
          "values": false
        },
        "colorMode": "background",
        "graphMode": "none"
      }
    },
    {
      "type": "stat",
      "title": "WS 连",
      "id": 1105,
      "gridPos": {
        "h": 4,
        "w": 2,
        "x": 8,
        "y": 1
      },
      "datasource": {
        "type": "prometheus",
        "uid": "prometheus-monitoring"
      },
      "targets": [
        {
          "refId": "A",
          "expr": "min(mlbot_ws_connected{job=\"quant-feature-bus\"})",
          "instant": true,
          "legendFormat": "WS 连"
        }
      ],
      "fieldConfig": {
        "defaults": {
          "min": 0,
          "max": 1.0,
          "decimals": 0,
          "thresholds": {
            "mode": "absolute",
            "steps": [
              {
                "color": "red",
                "value": null
              },
              {
                "color": "green",
                "value": 1
              }
            ]
          }
        },
        "overrides": []
      },
      "options": {
        "reduceOptions": {
          "calcs": [
            "lastNotNull"
          ],
          "values": false
        },
        "colorMode": "background",
        "graphMode": "none"
      }
    },
    {
      "type": "stat",
      "title": "新鲜",
      "id": 1106,
      "gridPos": {
        "h": 4,
        "w": 2,
        "x": 10,
        "y": 1
      },
      "datasource": {
        "type": "prometheus",
        "uid": "prometheus-monitoring"
      },
      "targets": [
        {
          "refId": "A",
          "expr": "min(mlbot_pipeline_data_fresh{job=\"quant-feature-bus\"})",
          "instant": true,
          "legendFormat": "新鲜"
        }
      ],
      "fieldConfig": {
        "defaults": {
          "min": 0,
          "max": 1.0,
          "decimals": 0,
          "thresholds": {
            "mode": "absolute",
            "steps": [
              {
                "color": "red",
                "value": null
              },
              {
                "color": "green",
                "value": 1
              }
            ]
          }
        },
        "overrides": []
      },
      "options": {
        "reduceOptions": {
          "calcs": [
            "lastNotNull"
          ],
          "values": false
        },
        "colorMode": "background",
        "graphMode": "none"
      }
    },
    {
      "type": "stat",
      "title": "Tr 消费",
      "id": 1107,
      "gridPos": {
        "h": 4,
        "w": 2,
        "x": 12,
        "y": 1
      },
      "datasource": {
        "type": "prometheus",
        "uid": "prometheus-monitoring"
      },
      "targets": [
        {
          "refId": "A",
          "expr": "sum(rate(mlbot_bars_processed_total{job=\"quant-trend-fattail\"}[5m])) > bool 0",
          "instant": true,
          "legendFormat": "Tr 消费"
        }
      ],
      "fieldConfig": {
        "defaults": {
          "min": 0,
          "max": 1.0,
          "decimals": 0,
          "thresholds": {
            "mode": "absolute",
            "steps": [
              {
                "color": "red",
                "value": null
              },
              {
                "color": "green",
                "value": 1
              }
            ]
          }
        },
        "overrides": []
      },
      "options": {
        "reduceOptions": {
          "calcs": [
            "lastNotNull"
          ],
          "values": false
        },
        "colorMode": "background",
        "graphMode": "none"
      }
    },
    {
      "type": "stat",
      "title": "Hg 消费",
      "id": 1108,
      "gridPos": {
        "h": 4,
        "w": 2,
        "x": 14,
        "y": 1
      },
      "datasource": {
        "type": "prometheus",
        "uid": "prometheus-monitoring"
      },
      "targets": [
        {
          "refId": "A",
          "expr": "(sum(rate(mlbot_multi_leg_bars_processed_total{job=\"quant-hedge-multileg\"}[5m])) + sum(rate(mlbot_multi_leg_daemon_polls_total{job=\"quant-hedge-multileg\"}[5m]))) > bool 0",
          "instant": true,
          "legendFormat": "Hg 消费"
        }
      ],
      "fieldConfig": {
        "defaults": {
          "min": 0,
          "max": 1.0,
          "decimals": 0,
          "thresholds": {
            "mode": "absolute",
            "steps": [
              {
                "color": "red",
                "value": null
              },
              {
                "color": "green",
                "value": 1
              }
            ]
          }
        },
        "overrides": []
      },
      "options": {
        "reduceOptions": {
          "calcs": [
            "lastNotNull"
          ],
          "values": false
        },
        "colorMode": "background",
        "graphMode": "none"
      }
    },
    {
      "type": "stat",
      "title": "Tr 账",
      "id": 1109,
      "gridPos": {
        "h": 4,
        "w": 2,
        "x": 16,
        "y": 1
      },
      "datasource": {
        "type": "prometheus",
        "uid": "prometheus-monitoring"
      },
      "targets": [
        {
          "refId": "A",
          "expr": "min(mlbot_reconciliation_ok{job=\"quant-trend-fattail\",scope=\"trend\"})",
          "instant": true,
          "legendFormat": "Tr 账"
        }
      ],
      "fieldConfig": {
        "defaults": {
          "min": 0,
          "max": 1.0,
          "decimals": 0,
          "thresholds": {
            "mode": "absolute",
            "steps": [
              {
                "color": "red",
                "value": null
              },
              {
                "color": "green",
                "value": 1
              }
            ]
          }
        },
        "overrides": []
      },
      "options": {
        "reduceOptions": {
          "calcs": [
            "lastNotNull"
          ],
          "values": false
        },
        "colorMode": "background",
        "graphMode": "none"
      }
    },
    {
      "type": "stat",
      "title": "Hg 账",
      "id": 1110,
      "gridPos": {
        "h": 4,
        "w": 2,
        "x": 18,
        "y": 1
      },
      "datasource": {
        "type": "prometheus",
        "uid": "prometheus-monitoring"
      },
      "targets": [
        {
          "refId": "A",
          "expr": "min(mlbot_reconciliation_ok{job=\"quant-hedge-multileg\",scope=\"hedge\"})",
          "instant": true,
          "legendFormat": "Hg 账"
        }
      ],
      "fieldConfig": {
        "defaults": {
          "min": 0,
          "max": 1.0,
          "decimals": 0,
          "thresholds": {
            "mode": "absolute",
            "steps": [
              {
                "color": "red",
                "value": null
              },
              {
                "color": "green",
                "value": 1
              }
            ]
          }
        },
        "overrides": []
      },
      "options": {
        "reduceOptions": {
          "calcs": [
            "lastNotNull"
          ],
          "values": false
        },
        "colorMode": "background",
        "graphMode": "none"
      }
    },
    {
      "type": "stat",
      "title": "Sp 账",
      "id": 1111,
      "gridPos": {
        "h": 4,
        "w": 2,
        "x": 20,
        "y": 1
      },
      "datasource": {
        "type": "prometheus",
        "uid": "prometheus-monitoring"
      },
      "targets": [
        {
          "refId": "A",
          "expr": "min(mlbot_reconciliation_ok{job=\"quant-spot-accum\",scope=\"spot\"})",
          "instant": true,
          "legendFormat": "Sp 账"
        }
      ],
      "fieldConfig": {
        "defaults": {
          "min": 0,
          "max": 1.0,
          "decimals": 0,
          "thresholds": {
            "mode": "absolute",
            "steps": [
              {
                "color": "red",
                "value": null
              },
              {
                "color": "green",
                "value": 1
              }
            ]
          }
        },
        "overrides": []
      },
      "options": {
        "reduceOptions": {
          "calcs": [
            "lastNotNull"
          ],
          "values": false
        },
        "colorMode": "background",
        "graphMode": "none"
      }
    },
    {
      "type": "stat",
      "title": "管线新鲜 (1=OK)",
      "id": 1199,
      "gridPos": {
        "h": 5,
        "w": 12,
        "x": 0,
        "y": 24
      },
      "datasource": {
        "type": "prometheus",
        "uid": "prometheus-monitoring"
      },
      "targets": [
        {
          "refId": "A",
          "expr": "min by (pipeline) (mlbot_pipeline_data_fresh{job=\"quant-feature-bus\"})",
          "legendFormat": "{{pipeline}}"
        }
      ],
      "fieldConfig": {
        "defaults": {
          "min": 0,
          "max": 1,
          "decimals": 0,
          "thresholds": {
            "mode": "absolute",
            "steps": [
              {
                "color": "red",
                "value": null
              },
              {
                "color": "green",
                "value": 1
              }
            ]
          }
        },
        "overrides": []
      },
      "options": {
        "reduceOptions": {
          "calcs": [
            "lastNotNull"
          ],
          "values": false
        },
        "colorMode": "background",
        "graphMode": "none",
        "orientation": "horizontal"
      }
    },
    {
      "type": "timeseries",
      "title": "数据管线滞后 (秒)",
      "id": 120,
      "gridPos": {
        "h": 5,
        "w": 12,
        "x": 12,
        "y": 29
      },
      "datasource": {
        "type": "prometheus",
        "uid": "prometheus-monitoring"
      },
      "targets": [
        {
          "refId": "A",
          "expr": "mlbot_pipeline_data_age_seconds{job=\"quant-feature-bus\"}",
          "legendFormat": "{{pipeline}} {{symbol}}"
        }
      ],
      "fieldConfig": {
        "defaults": {
          "unit": "s"
        },
        "overrides": []
      }
    },
    {
      "type": "stat",
      "title": "Publisher · Target UP",
      "id": 1081,
      "gridPos": {
        "h": 6,
        "w": 4,
        "x": 12,
        "y": 44
      },
      "datasource": {
        "type": "prometheus",
        "uid": "prometheus-monitoring"
      },
      "targets": [
        {
          "refId": "A",
          "expr": "up{job=\"quant-feature-bus\"}",
          "instant": true
        }
      ],
      "fieldConfig": {
        "defaults": {
          "min": 0,
          "max": 1,
          "thresholds": {
            "mode": "absolute",
            "steps": [
              {
                "color": "red",
                "value": null
              },
              {
                "color": "green",
                "value": 1
              }
            ]
          }
        },
        "overrides": []
      },
      "options": {
        "reduceOptions": {
          "calcs": [
            "lastNotNull"
          ],
          "values": false
        },
        "colorMode": "background",
        "graphMode": "none"
      }
    },
    {
      "type": "timeseries",
      "title": "Publisher · CPU / RSS",
      "id": 1082,
      "gridPos": {
        "h": 6,
        "w": 8,
        "x": 16,
        "y": 44
      },
      "datasource": {
        "type": "prometheus",
        "uid": "prometheus-monitoring"
      },
      "targets": [
        {
          "refId": "A",
          "expr": "mlbot_cpu_percent{job=\"quant-feature-bus\"}",
          "legendFormat": "cpu %"
        },
        {
          "refId": "B",
          "expr": "mlbot_memory_rss_mb{job=\"quant-feature-bus\"}",
          "legendFormat": "rss MB"
        }
      ],
      "fieldConfig": {
        "defaults": {},
        "overrides": [
          {
            "matcher": {
              "id": "byName",
              "options": "rss MB"
            },
            "properties": [
              {
                "id": "unit",
                "value": "decmbytes"
              },
              {
                "id": "custom.axisPlacement",
                "value": "right"
              }
            ]
          },
          {
            "matcher": {
              "id": "byName",
              "options": "cpu %"
            },
            "properties": [
              {
                "id": "unit",
                "value": "percent"
              }
            ]
          }
        ]
      }
    },
    {
      "type": "row",
      "title": "Trend · 方向账户 (quant-trend-fattail)",
      "id": 3010,
      "gridPos": {
        "h": 1,
        "w": 24,
        "x": 0,
        "y": 50
      },
      "collapsed": false
    },
    {
      "type": "stat",
      "title": "Trend · Target UP",
      "id": 301,
      "gridPos": {
        "h": 4,
        "w": 4,
        "x": 0,
        "y": 51
      },
      "datasource": {
        "type": "prometheus",
        "uid": "prometheus-monitoring"
      },
      "targets": [
        {
          "refId": "A",
          "expr": "up{job=\"quant-trend-fattail\"}",
          "instant": true
        }
      ],
      "fieldConfig": {
        "defaults": {
          "min": 0,
          "max": 1,
          "thresholds": {
            "mode": "absolute",
            "steps": [
              {
                "color": "red",
                "value": null
              },
              {
                "color": "green",
                "value": 1
              }
            ]
          }
        },
        "overrides": []
      },
      "options": {
        "reduceOptions": {
          "calcs": [
            "lastNotNull"
          ],
          "values": false
        },
        "colorMode": "background",
        "graphMode": "none"
      }
    },
    {
      "type": "timeseries",
      "title": "Trend · Feature Bus 滞后 (读 bus)",
      "id": 302,
      "gridPos": {
        "h": 6,
        "w": 10,
        "x": 4,
        "y": 51
      },
      "datasource": {
        "type": "prometheus",
        "uid": "prometheus-monitoring"
      },
      "targets": [
        {
          "refId": "A",
          "expr": "mlbot_feature_bus_snapshot_age_seconds{job=\"quant-trend-fattail\"}",
          "legendFormat": "{{symbol}}"
        }
      ],
      "fieldConfig": {
        "defaults": {
          "unit": "s"
        },
        "overrides": []
      }
    },
    {
      "type": "timeseries",
      "title": "Trend · System Mode",
      "id": 303,
      "gridPos": {
        "h": 6,
        "w": 5,
        "x": 14,
        "y": 51
      },
      "datasource": {
        "type": "prometheus",
        "uid": "prometheus-monitoring"
      },
      "targets": [
        {
          "refId": "A",
          "expr": "mlbot_system_mode{job=\"quant-trend-fattail\"}",
          "legendFormat": "mode"
        }
      ],
      "fieldConfig": {
        "defaults": {
          "min": 0,
          "max": 2
        },
        "overrides": []
      }
    },
    {
      "type": "timeseries",
      "title": "Trend · CPU / RSS",
      "id": 304,
      "gridPos": {
        "h": 6,
        "w": 5,
        "x": 19,
        "y": 51
      },
      "datasource": {
        "type": "prometheus",
        "uid": "prometheus-monitoring"
      },
      "targets": [
        {
          "refId": "A",
          "expr": "mlbot_cpu_percent{job=\"quant-trend-fattail\"}",
          "legendFormat": "cpu"
        },
        {
          "refId": "B",
          "expr": "mlbot_memory_rss_mb{job=\"quant-trend-fattail\"}",
          "legendFormat": "rss"
        }
      ],
      "fieldConfig": {
        "defaults": {},
        "overrides": []
      }
    },
    {
      "type": "timeseries",
      "title": "Trend · Bars 吞吐",
      "id": 305,
      "gridPos": {
        "h": 5,
        "w": 12,
        "x": 0,
        "y": 57
      },
      "datasource": {
        "type": "prometheus",
        "uid": "prometheus-monitoring"
      },
      "targets": [
        {
          "refId": "A",
          "expr": "rate(mlbot_bars_processed_total{job=\"quant-trend-fattail\"}[5m])",
          "legendFormat": "bars/s"
        }
      ],
      "fieldConfig": {
        "defaults": {},
        "overrides": []
      }
    },
    {
      "type": "row",
      "title": "Multi-leg · 对冲账户 (quant-hedge-multileg)",
      "id": 4010,
      "gridPos": {
        "h": 1,
        "w": 24,
        "x": 0,
        "y": 62
      },
      "collapsed": false
    },
    {
      "type": "stat",
      "title": "Multi-leg · Target UP",
      "id": 401,
      "gridPos": {
        "h": 4,
        "w": 4,
        "x": 0,
        "y": 63
      },
      "datasource": {
        "type": "prometheus",
        "uid": "prometheus-monitoring"
      },
      "targets": [
        {
          "refId": "A",
          "expr": "up{job=\"quant-hedge-multileg\"}",
          "instant": true
        }
      ],
      "fieldConfig": {
        "defaults": {
          "min": 0,
          "max": 1,
          "thresholds": {
            "mode": "absolute",
            "steps": [
              {
                "color": "red",
                "value": null
              },
              {
                "color": "green",
                "value": 1
              }
            ]
          }
        },
        "overrides": []
      },
      "options": {
        "reduceOptions": {
          "calcs": [
            "lastNotNull"
          ],
          "values": false
        },
        "colorMode": "background",
        "graphMode": "none"
      }
    },
    {
      "type": "timeseries",
      "title": "Multi-leg · Bars 吞吐",
      "id": 402,
      "gridPos": {
        "h": 6,
        "w": 10,
        "x": 4,
        "y": 63
      },
      "datasource": {
        "type": "prometheus",
        "uid": "prometheus-monitoring"
      },
      "targets": [
        {
          "refId": "A",
          "expr": "sum(rate(mlbot_multi_leg_bars_processed_total{job=\"quant-hedge-multileg\"}[5m]))",
          "legendFormat": "bars/s"
        }
      ],
      "fieldConfig": {
        "defaults": {},
        "overrides": []
      }
    },
    {
      "type": "timeseries",
      "title": "Multi-leg · Daemon / Actions",
      "id": 403,
      "gridPos": {
        "h": 6,
        "w": 10,
        "x": 14,
        "y": 63
      },
      "datasource": {
        "type": "prometheus",
        "uid": "prometheus-monitoring"
      },
      "targets": [
        {
          "refId": "A",
          "expr": "rate(mlbot_multi_leg_daemon_polls_total{job=\"quant-hedge-multileg\"}[5m])",
          "legendFormat": "poll/s"
        },
        {
          "refId": "B",
          "expr": "sum by (strategy, symbol) (rate(mlbot_multi_leg_actions_total{job=\"quant-hedge-multileg\"}[5m]))",
          "legendFormat": "{{strategy}} {{symbol}}"
        }
      ],
      "fieldConfig": {
        "defaults": {},
        "overrides": []
      }
    },
    {
      "type": "timeseries",
      "title": "Multi-leg · CPU / RSS",
      "id": 404,
      "gridPos": {
        "h": 6,
        "w": 4,
        "x": 19,
        "y": 63
      },
      "datasource": {
        "type": "prometheus",
        "uid": "prometheus-monitoring"
      },
      "targets": [
        {
          "refId": "A",
          "expr": "mlbot_cpu_percent{job=\"quant-hedge-multileg\"}",
          "legendFormat": "cpu"
        },
        {
          "refId": "B",
          "expr": "mlbot_memory_rss_mb{job=\"quant-hedge-multileg\"}",
          "legendFormat": "rss"
        }
      ],
      "fieldConfig": {
        "defaults": {},
        "overrides": []
      }
    },
    {
      "type": "row",
      "title": "Spot · 现货吸筹 (quant-spot-accum)",
      "id": 5010,
      "gridPos": {
        "h": 1,
        "w": 24,
        "x": 0,
        "y": 74
      },
      "collapsed": false
    },
    {
      "type": "stat",
      "title": "Spot · Target UP",
      "id": 501,
      "gridPos": {
        "h": 4,
        "w": 4,
        "x": 0,
        "y": 75
      },
      "datasource": {
        "type": "prometheus",
        "uid": "prometheus-monitoring"
      },
      "targets": [
        {
          "refId": "A",
          "expr": "up{job=\"quant-spot-accum\"}",
          "instant": true
        }
      ],
      "fieldConfig": {
        "defaults": {
          "min": 0,
          "max": 1,
          "thresholds": {
            "mode": "absolute",
            "steps": [
              {
                "color": "red",
                "value": null
              },
              {
                "color": "green",
                "value": 1
              }
            ]
          }
        },
        "overrides": []
      },
      "options": {
        "reduceOptions": {
          "calcs": [
            "lastNotNull"
          ],
          "values": false
        },
        "colorMode": "background",
        "graphMode": "none"
      }
    },
    {
      "type": "timeseries",
      "title": "Spot · Feature Bus 滞后 (读 bus)",
      "id": 502,
      "gridPos": {
        "h": 6,
        "w": 10,
        "x": 4,
        "y": 75
      },
      "datasource": {
        "type": "prometheus",
        "uid": "prometheus-monitoring"
      },
      "targets": [
        {
          "refId": "A",
          "expr": "mlbot_feature_bus_snapshot_age_seconds{job=\"quant-spot-accum\"}",
          "legendFormat": "{{symbol}}"
        }
      ],
      "fieldConfig": {
        "defaults": {
          "unit": "s"
        },
        "overrides": []
      }
    },
    {
      "type": "stat",
      "title": "Spot · 对账 OK",
      "id": 503,
      "gridPos": {
        "h": 6,
        "w": 4,
        "x": 14,
        "y": 75
      },
      "datasource": {
        "type": "prometheus",
        "uid": "prometheus-monitoring"
      },
      "targets": [
        {
          "refId": "A",
          "expr": "min(mlbot_reconciliation_ok{job=\"quant-spot-accum\",scope=\"spot\"})",
          "instant": true
        }
      ],
      "fieldConfig": {
        "defaults": {
          "min": 0,
          "max": 1,
          "mappings": [
            {
              "type": "value",
              "options": {
                "0": {
                  "text": "需人工检查",
                  "color": "red",
                  "index": 0
                },
                "1": {
                  "text": "正常",
                  "color": "green",
                  "index": 1
                }
              }
            }
          ],
          "thresholds": {
            "mode": "absolute",
            "steps": [
              {
                "color": "red",
                "value": null
              },
              {
                "color": "green",
                "value": 1
              }
            ]
          }
        },
        "overrides": []
      },
      "options": {
        "reduceOptions": {
          "calcs": [
            "lastNotNull"
          ],
          "values": false
        },
        "colorMode": "background",
        "graphMode": "none"
      }
    },
    {
      "type": "timeseries",
      "title": "Spot · CPU / RSS",
      "id": 504,
      "gridPos": {
        "h": 6,
        "w": 6,
        "x": 18,
        "y": 75
      },
      "datasource": {
        "type": "prometheus",
        "uid": "prometheus-monitoring"
      },
      "targets": [
        {
          "refId": "A",
          "expr": "mlbot_cpu_percent{job=\"quant-spot-accum\"}",
          "legendFormat": "cpu"
        },
        {
          "refId": "B",
          "expr": "mlbot_memory_rss_mb{job=\"quant-spot-accum\"}",
          "legendFormat": "rss"
        }
      ],
      "fieldConfig": {
        "defaults": {},
        "overrides": []
      }
    },
    {
      "type": "table",
      "title": "Spot · 对账问题明细",
      "id": 505,
      "gridPos": {
        "h": 5,
        "w": 24,
        "x": 0,
        "y": 81
      },
      "datasource": {
        "type": "prometheus",
        "uid": "prometheus-monitoring"
      },
      "targets": [
        {
          "refId": "A",
          "expr": "mlbot_reconciliation_issue_count{job=\"quant-spot-accum\",scope=\"spot\"} > 0",
          "format": "table",
          "instant": true
        }
      ],
      "fieldConfig": {
        "defaults": {},
        "overrides": []
      },
      "options": {
        "showHeader": true
      }
    },
    {
      "type": "text",
      "title": "看板说明",
      "id": 506,
      "gridPos": {
        "h": 2,
        "w": 24,
        "x": 0,
        "y": 86
      },
      "options": {
        "mode": "markdown",
        "content": "**分区说明**：上方为全局与 **feature-bus 发布端**；下方三块按进程拆分 — **Trend**（`quant-trend-fattail`）、**Multi-leg**（`quant-hedge-multileg`）、**Spot**（`quant-spot-accum`）。某块 Target UP 变红或 Bus 滞后尖峰时，优先查对应容器 `docker logs`。"
      }
    }
  ],
  "schemaVersion": 39,
  "style": "dark",
  "tags": [
    "quant",
    "system",
    "core"
  ],
  "templating": {
    "list": []
  },
  "time": {
    "from": "now-6h",
    "to": "now"
  },
  "timepicker": {},
  "timezone": "utc",
  "title": "System Health · 运维总览",
  "uid": "quant-system",
  "version": 6
}
